cybosx_login/__init__.py
cybosx_login/cybosx_login.py
cybosx_login/cybosx_path.py
cybosx_login/cybosx_process.py
cybosx_login-0.1.0.dist-info/LICENSE
cybosx_login-0.1.0.dist-info/METADATA
cybosx_login-0.1.0.dist-info/WHEEL
cybosx_login-0.1.0.dist-info/RECORD
