Metadata-Version: 2.1
Name: cybosx-login
Version: 0.1.0
Summary: Dhashin Cybosplus login automation 대신 사이보스플러스 자동 로그인
Home-page: https://github.com/th-yoo/cybosx_login
License: MIT
Keywords: daishin,cybosplus,login,automation,대신,사이보플러스,로그인,자동화
Author: th yoo
Author-email: taihyungyoo@gmail.com
Requires-Python: >=3.9,<4.0
Classifier: License :: OSI Approved :: MIT License
Classifier: Programming Language :: Python :: 3
Classifier: Programming Language :: Python :: 3.9
Classifier: Programming Language :: Python :: 3.10
Classifier: Programming Language :: Python :: 3.11
Classifier: Programming Language :: Python :: 3.12
Requires-Dist: pywin32 (>=300) ; sys_platform == "win32"
Requires-Dist: run-as-task (>=0.1.4,<0.2.0) ; sys_platform == "win32"
Requires-Dist: win-auto-tiny (>=0.1.2,<0.2.0) ; sys_platform == "win32"
